.venv/lib/python3.10/site-packages/attr/__init__.pyi
.venv/lib/python3.10/site-packages/attr/_cmp.pyi
.venv/lib/python3.10/site-packages/attr/_version_info.pyi
.venv/lib/python3.10/site-packages/attr/converters.pyi
.venv/lib/python3.10/site-packages/attr/exceptions.pyi
.venv/lib/python3.10/site-packages/attr/filters.pyi
.venv/lib/python3.10/site-packages/attr/setters.pyi
.venv/lib/python3.10/site-packages/attr/validators.pyi
.venv/lib/python3.10/site-packages/attrs/__init__.pyi
.venv/lib/python3.10/site-packages/mypy/typeshed/stdlib/__future__.pyi
.venv/lib/python3.10/site-packages/mypy/typeshed/stdlib/__main__.pyi
.venv/lib/python3.10/site-packages/mypy/typeshed/stdlib/_ast.pyi
.venv/lib/python3.10/site-packages/mypy/typeshed/stdlib/_bisect.pyi
.venv/lib/python3.10/site-packages/mypy/typeshed/stdlib/_bootlocale.pyi
.venv/lib/python3.10/site-packages/mypy/typeshed/stdlib/_codecs.pyi
.venv/lib/python3.10/site-packages/mypy/typeshed/stdlib/_collections_abc.pyi
.venv/lib/python3.10/site-packages/mypy/typeshed/stdlib/_compat_pickle.pyi
.venv/lib/python3.10/site-packages/mypy/typeshed/stdlib/_compression.pyi
.venv/lib/python3.10/site-packages/mypy/typeshed/stdlib/_csv.pyi
.venv/lib/python3.10/site-packages/mypy/typeshed/stdlib/_ctypes.pyi
.venv/lib/python3.10/site-packages/mypy/typeshed/stdlib/_curses.pyi
.venv/lib/python3.10/site-packages/mypy/typeshed/stdlib/_decimal.pyi
.venv/lib/python3.10/site-packages/mypy/typeshed/stdlib/_dummy_thread.pyi
.venv/lib/python3.10/site-packages/mypy/typeshed/stdlib/_dummy_threading.pyi
.venv/lib/python3.10/site-packages/mypy/typeshed/stdlib/_heapq.pyi
.venv/lib/python3.10/site-packages/mypy/typeshed/stdlib/_imp.pyi
.venv/lib/python3.10/site-packages/mypy/typeshed/stdlib/_json.pyi
.venv/lib/python3.10/site-packages/mypy/typeshed/stdlib/_locale.pyi
.venv/lib/python3.10/site-packages/mypy/typeshed/stdlib/_markupbase.pyi
.venv/lib/python3.10/site-packages/mypy/typeshed/stdlib/_msi.pyi
nwon_baseline-0.2.15.dist-info/METADATA
nwon_baseline-0.2.15.dist-info/WHEEL
nwon_baseline-0.2.15.dist-info/entry_points.txt
nwon_baseline-0.2.15.dist-info/RECORD
