Metadata-Version: 2.1
Name: nwon_baseline
Version: 0.2.15
Summary: Python Code that is used in several projects
Home-page: https://nwon.de
License: MIT
Author: Reik Stiebeling
Author-email: reik.stiebeling@nwon.de
Requires-Python: >=3.8,<4.0
Classifier: License :: OSI Approved :: MIT License
Classifier: Programming Language :: Python :: 3
Classifier: Programming Language :: Python :: 3.8
Classifier: Programming Language :: Python :: 3.9
Classifier: Programming Language :: Python :: 3.10
Classifier: Programming Language :: Python :: 3.11
Classifier: Programming Language :: Python :: 3.12
Requires-Dist: jsonref (>=1.1.0,<2.0.0)
Requires-Dist: pydantic (>=2.0.0,<3.0.0)
Requires-Dist: pytz (>=2022.1,<2023.0)
Project-URL: Repository, https://gitlab.com/nvon/pypi-packages/nwon_baseline
